bst_helper_functions/bst_att_est.py
bst_helper_functions/dem_utils.py
bst_helper_functions/geometry_utils.py
bst_helper_functions/gis_utils.py
bst_helper_functions-0.0.2.dist-info/licenses/LICENSE
bst_helper_functions-0.0.2.dist-info/METADATA
bst_helper_functions-0.0.2.dist-info/WHEEL
bst_helper_functions-0.0.2.dist-info/top_level.txt
bst_helper_functions-0.0.2.dist-info/RECORD
