Metadata-Version: 2.4
Name: bst_helper_functions
Version: 0.0.2
Summary: Black Swift Technologies Helper Tools
Author-email: Maciej Stachura <stachura@blackswifttech.com>, Jack Elston <elstonj@blackswifttech.com>, Ben Busby <ben.busby@blackswifttech.com>
Project-URL: Homepage, https://bst.aero
Project-URL: Issues, https://bst.aero/support
Classifier: Programming Language :: Python :: 3
Classifier: Operating System :: POSIX
Requires-Python: >=3.8
License-File: LICENSE
Requires-Dist: numpy
Requires-Dist: pyproj
Dynamic: license-file
